LICENSE
MANIFEST.in
README.rst
setup.py
django_weixin/Sample.py
django_weixin/WXBizMsgCrypt.py
django_weixin/__init__.py
django_weixin/address_book.py
django_weixin/admin.py
django_weixin/api_errors.py
django_weixin/ierror.py
django_weixin/tests.py
django_weixin/urls.py
django_weixin.egg-info/PKG-INFO
django_weixin.egg-info/SOURCES.txt
django_weixin.egg-info/dependency_links.txt
django_weixin.egg-info/top_level.txt